{
  "Gender":{
    "id":1
  },
  "Language":{
    "id":2
  },
  "Religion":{
    "id":3
  },
  "Manner of death":{
    "id":4
  },
  "Cause of death": {
    "id":5
  },
  "Life event type": {
    "id":6
  },
  "Literary event type":{
    "id":7
  },
  "Periodicity":{
    "id":8
  },
  "Occupation": {
    "id":9
  },
  "Literary movement": {
    "id":10
  },
  "Type of institution":{
    "id":11
  },
  "Periodical type":{
    "id":12
  },
  "Genre":{
    "id":13
  },
  "Theme":{
    "id":14
  },
  "Format":{
    "id":15
  },
  "Type of ephemeral":{
    "id":16
  },
  "Type of contribution":{
    "id":17
  },
  "Type of book":{
    "id":18
  },
  "Type of book series":{
    "id":19
  },
  "Type of article":{
    "id":20
  },
  "Country": {
    "Palestine": "https://www.geonames.org/6254930/palestine.html",
    "United States": "https://www.geonames.org/6252001/united-states.html",
    "Tunisia": "https://www.geonames.org/2464461/republic-of-tunisia.html",
    "Syria": "https://www.geonames.org/163843/syrian-arab-republic.html",
    "Portugal": "https://www.geonames.org/2264397/portuguese-republic.html",
    "Nigeria": "https://www.geonames.org/2328926/federal-republic-of-nigeria.html",
    "Lebanon": "https://www.geonames.org/272103/lebanon.html",
    "Kuwait": "https://www.geonames.org/285570/state-of-kuwait.html",
    "Jordan": "https://www.geonames.org/248816/hashemite-kingdom-of-jordan.html",
    "Israel": "https://www.geonames.org/294640/state-of-israel.html",
    "Iraq": "https://www.geonames.org/99237/republic-of-iraq.html",
    "France": "https://www.geonames.org/3017382/republic-of-france.html",
    "Egypt": "https://www.geonames.org/357994/arab-republic-of-egypt.html",
    "Denmark": "https://www.geonames.org/2623032/kingdom-of-denmark.html",
    "Canada": "https://www.geonames.org/6251999/canada.html",
    "Algeria": "https://www.geonames.org/2589581/algeria.html",
    "United Kingdom": "https://www.geonames.org/2635167/united-kingdom-of-great-britain-and-northern-ireland.html",
    "Soviet Union": "http://www.geonames.org/8354411/union-of-soviet-socialist-republics.html",
    "Ukraine": "https://www.geonames.org/690791/ukraine.html",
    "Saudi Arabia": "https://www.geonames.org/102358/kingdom-of-saudi-arabia.html",
    "Poland": "https://www.geonames.org/798544/republic-of-poland.html",
    "Morocco": "https://www.geonames.org/2542007/kingdom-of-morocco.html",
    "Haiti": "https://www.geonames.org/3723988/republic-of-haiti.html",
    "Switzerland": "https://www.geonames.org/2658434/switzerland.html",
    "Spain": "https://www.geonames.org/2510769/kingdom-of-spain.html",
    "Italy": "https://www.geonames.org/3175395/italian-republic.html",
    "Hungary": "https://www.geonames.org/719819/hungary.html",
    "Greece": "https://www.geonames.org/390903/hellenic-republic.html",
    "Germany": "https://www.geonames.org/2921044/federal-republic-of-germany.html",
    "Cyprus": "https://www.geonames.org/146669/republic-of-cyprus.html",
    "Belgium": "https://www.geonames.org/2802361/kingdom-of-belgium.html",
    "United Arab Emirates": "https://www.geonames.org/290557/united-arab-emirates.html",
    "Sweden": "https://www.geonames.org/2661886/kingdom-of-sweden.html",
    "Sudan": "https://www.geonames.org/366755/republic-of-the-sudan.html",
    "Mexico": "https://www.geonames.org/3996063/mexico.html",
    "Qatar": "https://www.geonames.org/289688/state-of-qatar.html",
    "Bulgaria":"https://www.geonames.org/732800/republic-of-bulgaria.html",
    "Austria": "https://www.geonames.org/2782113/republic-of-austria.html"
  },
  "Palestine district": {
    "Gaza":"openmaps Palestine - district",
    "Bologna":"geonames - district"
  },
  "City": {
    "St. Louis": "https://www.geonames.org/4407066/st-louis.html",
    "Salamiyah": "https://www.geonames.org/164946/al-salamiyah-district.html",
    "Rabat": "https://www.geonames.org/2538475/rabat.html",
    "Qamishli": "https://www.geonames.org/12094942/wadi-qamishli.html",
    "Paris": "http://www.geonames.org/2988506/paris.html",
    "New York City": "https://www.geonames.org/5128581/new-york-city.html",
    "Masyaf": "https://www.geonames.org/167044/masyaf-district.html",
    "Ma'in": "http://www.geonames.org/10862119/qada-ma-in.html",
    "Los Angeles": "https://www.geonames.org/5368361/los-angeles.html",
    "Khenchara": "http://www.geonames.org/279737/el-khenchara.html",
    "Kharaba": "https://www.geonames.org/11864962/kharaba.html",
    "Hailey": "https://www.geonames.org/5594956/hailey.html",
    "Damascus": "https://www.geonames.org/170654/damascus.html",
    "Cleveland": "http://www.geonames.org/5150529/cleveland.html",
    "Cairo": "https://www.geonames.org/360630/cairo.html",
    "Beirut": "https://www.geonames.org/276781/beirut.html",
    "Baskinta": "http://www.geonames.org/6276828/morh-baskinta.html",
    "Baghdad": "https://www.geonames.org/98182/baghdad.html",
    "Azinhaga": "https://www.geonames.org/8013013/azinhaga.html",
    "Az Zarqa": "https://www.geonames.org/250090/zarqa.html",
    "Amman": "https://www.geonames.org/250441/amman.html",
    "Alexandria": "https://www.geonames.org/361058/alexandria.html",
    "Al-Salt": "https://www.geonames.org/250258/as-salt.html",
    "Ain Anoub": "https://www.geonames.org/277434/ain-aanoub.html",
    "Abeokuta": "https://www.geonames.org/2352947/abeokuta.html",
    "Washington D.C.": "https://www.geonames.org/4140963/washington.html",
    "Tunis": "https://www.geonames.org/2464470/tunis.html",
    "Toronto": "https://www.geonames.org/6167865/toronto.html",
    "Seattle": "https://www.geonames.org/5809844/seattle.html",
    "Salt Lake City": "https://www.geonames.org/5780993/salt-lake-city.html",
    "Rome": "https://www.geonames.org/3169070/rome.html",
    "Riyadh": "https://www.geonames.org/108410/riyadh.html",
    "Nicosia": "https://www.geonames.org/146268/nicosia.html",
    "Montreal": "https://www.geonames.org/6077243/montreal.html",
    "Mexico City": "https://www.geonames.org/3527646/ciudad-de-mexico.html",
    "London": "https://www.geonames.org/2643743/london.html",
    "Kuwait City": "https://www.geonames.org/285787/kuwait-city.html",
    "Khartoum": "https://www.geonames.org/379252/khartoum.html",
    "Hartford": "https://www.geonames.org/4835797/hartford.html",
    "Constantine": "https://www.geonames.org/2501152/constantine.html",
    "Calgary": "https://www.geonames.org/5913490/calgary.html",
    "Bonn": "https://www.geonames.org/3247450/kreisfreie-stadt-bonn.html",
    "Berlin": "https://www.geonames.org/2950159/berlin.html",
    "Basra": "https://www.geonames.org/99532/basrah.html",
    "Austin": "https://www.geonames.org/4671654/austin.html",
    "Ann Arbor": "https://www.geonames.org/4984247/ann-arbor.html",
    "Alger": "https://www.geonames.org/2507480/algiers.html",
    "Abu Dhabi": "https://www.geonames.org/292968/abu-dhabi.html",
    "Vancouver": "https://www.geonames.org/6173331/vancouver.html",
    "Oxford": "https://www.geonames.org/2640729/oxford.html",
    "Manchester": "https://www.geonames.org/2643123/manchester.html",
    "Cambridge, Massachusetts": "https://www.geonames.org/4931972/cambridge.html",
    "Burnaby": "https://www.geonames.org/5911606/burnaby.html",
    "Tetouan": "https://www.geonames.org/2528910/tetouan.html",
    "Ottawa": "https://www.geonames.org/6094817/ottawa.html",
    "Jeddah": "https://www.geonames.org/105343/jeddah.html",
    "Dubai": "https://www.geonames.org/292224/dubai.html",
    "Dresden": "https://www.geonames.org/2935020/kreisfreie-stadt-dresden.html",
    "Doha": "https://www.geonames.org/290030/doha.html",
    "Azzarqa": "https://www.geonames.org/250090/zarqa.html",
    "Aleppo": "https://www.geonames.org/170063/aleppo.html",
    "Vienna": "https://www.geonames.org/2761369/vienna.html",
    "Sofia": "https://www.geonames.org/727011/sofia.html",
    "Jundubah": "https://www.geonames.org/2470086/jendouba.html",
    "Hammamet": "https://www.geonames.org/2473744/hammamet.html"
  }
}
